kake.py
kake-0.1.dist-info/METADATA
kake-0.1.dist-info/WHEEL
kake-0.1.dist-info/top_level.txt
kake-0.1.dist-info/RECORD
