Metadata-Version: 2.1
Name: kake
Version: 0.1
Summary: Klinoff Application Konstruction Engine
Author: Jooapa
